
        [
            
                    {
                        "name":"TACTICAL WEAPON 4X30MM MILDOT RETICLE W/RINGS AR  SKS MOUNT | 6.31618E+11",
                        "image": "https://cdn-cumulusdata.celerantwebservices.com/CAPRODIMAGES/OSTW4X30.jpg",
                        "available":"Out of Stock",
                        "id":"262631",
                        "brand":"BSA",
                        "upc":"6.31618E+11",
                        "price":null,
                        "Dept":"Optics",
                        "Typ":"Scopes",
                        "SUBTYP_1":"Rifle",
                        "product_url":"/product/262631/TACTICALWEAPON4X30MMMILDOTRETICLEWRINGSARSKSMOUNT",
                        "attributes": 
                        [
                            
                            {
                                "name":"Brand",
                                "value":"BSA"
                            }
                            
                        ]
                    }
                    
        ]
    
