
        [
            
                    {
                        "name":"SAVAGE MOD 220 THUMBHOLE 20 GAUGE 22 Inch BBL BLUED CARBON STEEL | 011356223135",
                        "image": "https://cdn-cumulusdata.celerantwebservices.com/SSPRODIMAGES/120293.jpg",
                        "available":"In Stock Vendor",
                        "id":"70040",
                        "brand":"SAVAGE",
                        "upc":"011356223135",
                        
                        "price":745.14,
                        "Dept":"Firearms",
                        "Typ":"Shotguns",
                        "SUBTYP_1":"Bolt",
                        "product_url":"/product/70040/SAVAGEMOD220THUMBHOLE20GAUGE22BBLBLUEDCARBONSTEEL",
                        
                        "attributes": 
                        [
                            
                                {
                                    "name":"Pickup In Store",
                                    "value":"Not Available"
                                },
                            
                                {
                                    "name":"Price Range",
                                    "value":"$701 and more"
                                },
                            
                            {
                                "name":"Brand",
                                "value":"SAVAGE"
                            }
                            
                        ]
                    }
                    , 
                    {
                        "name":"SAVAGE MOD 220 THUMBHOLE 20 GAUGE 22 Inch BBL STAINLESS STEEL | 011356223142",
                        "image": "https://cdn-cumulusdata.celerantwebservices.com/SSPRODIMAGES/120294.jpg",
                        "available":"Out of Stock",
                        "id":"70041",
                        "brand":"SAVAGE",
                        "upc":"011356223142",
                        
                        "price":null,
                        "Dept":"Firearms",
                        "Typ":"Shotguns",
                        "SUBTYP_1":"Bolt",
                        "product_url":"/product/70041/SAVAGEMOD220THUMBHOLE20GAUGE22BBLSTAINLESSSTEEL",
                        
                        "attributes": 
                        [
                            
                                {
                                    "name":"Pickup In Store",
                                    "value":"Not Available"
                                },
                            
                                {
                                    "name":"Price Range",
                                    "value":"$701 and more"
                                },
                            
                            {
                                "name":"Brand",
                                "value":"SAVAGE"
                            }
                            
                        ]
                    }
                    , 
                    {
                        "name":"Savage 220 Slug Gun 20ga 2rd Capacity 22 Inch Barrel  Black/Grey Synthetic Accustock | 011356573773",
                        "image": "https://cdn-cumulusdata.celerantwebservices.com/SSPRODIMAGES/108384.jpg",
                        "available":"Out of Stock",
                        "id":"98043",
                        "brand":"SAVAGE",
                        "upc":"011356573773",
                        
                        "price":null,
                        "Dept":"Firearms",
                        "Typ":"Shotguns",
                        "SUBTYP_1":"Bolt",
                        "product_url":"/product/98043/Savage220SlugGun20ga2rdCapacity22BarrelBlackGreySyntheticAccustock",
                        
                        "attributes": 
                        [
                            
                                {
                                    "name":"Pickup In Store",
                                    "value":"Not Available"
                                },
                            
                                {
                                    "name":"Price Range",
                                    "value":"$501-$700"
                                },
                            
                            {
                                "name":"Brand",
                                "value":"SAVAGE"
                            }
                            
                        ]
                    }
                    , 
                    {
                        "name":"Savage 220 Slug Left Hand Rifle 20ga 2rd Magazine 22 Inch Barrel Black Stock | 011356573780",
                        "image": "https://cdn-cumulusdata.celerantwebservices.com/SSPRODIMAGES/108385.jpg",
                        "available":"Out of Stock",
                        "id":"264378",
                        "brand":"SAVAGE",
                        "upc":"011356573780",
                        
                        "price":null,
                        "Dept":"Firearms",
                        "Typ":"Shotguns",
                        "SUBTYP_1":"Bolt",
                        "product_url":"/product/264378/Savage220SlugLeftHandRifle20ga2rdMagazine22BarrelBlackStock",
                        
                        "attributes": 
                        [
                            
                                {
                                    "name":"Pickup In Store",
                                    "value":"Not Available"
                                },
                            
                                {
                                    "name":"Price Range",
                                    "value":"$501-$700"
                                },
                            
                            {
                                "name":"Brand",
                                "value":"SAVAGE"
                            }
                            
                        ]
                    }
                    , 
                    {
                        "name":"Savage 220 Camo Slug Gun 20ga 2rd Capacity 22 Inch Barrel Mossy Oak Break Up Stock | 011356573803",
                        "image": "https://cdn-cumulusdata.celerantwebservices.com/SSPRODIMAGES/108387.jpg",
                        "available":"Out of Stock",
                        "id":"98049",
                        "brand":"SAVAGE",
                        "upc":"011356573803",
                        
                        "price":null,
                        "Dept":"Firearms",
                        "Typ":"Shotguns",
                        "SUBTYP_1":"Bolt",
                        "product_url":"/product/98049/Savage220CamoSlugGun20ga2rdCapacity22BarrelMossyOakBreakUpStock",
                        
                        "attributes": 
                        [
                            
                                {
                                    "name":"Pickup In Store",
                                    "value":"Not Available"
                                },
                            
                                {
                                    "name":"Price Range",
                                    "value":"$501-$700"
                                },
                            
                            {
                                "name":"Brand",
                                "value":"SAVAGE"
                            }
                            
                        ]
                    }
                    , 
                    {
                        "name":"Savage 220 Slug Gun 20ga 2rd Capacity 22 Inch Barrel Mossy Oak Break Up Synthetic Accustock | 011356573810",
                        "image": "https://cdn-cumulusdata.celerantwebservices.com/SSPRODIMAGES/108388.jpg",
                        "available":"Out of Stock",
                        "id":"98050",
                        "brand":"SAVAGE",
                        "upc":"011356573810",
                        
                        "price":null,
                        "Dept":"Firearms",
                        "Typ":"Shotguns",
                        "SUBTYP_1":"Bolt",
                        "product_url":"/product/98050/Savage220SlugGun20ga2rdCapacity22BarrelMossyOakBreakUpSyntheticAccustock",
                        
                        "attributes": 
                        [
                            
                                {
                                    "name":"Pickup In Store",
                                    "value":"Not Available"
                                },
                            
                                {
                                    "name":"Price Range",
                                    "value":"$701 and more"
                                },
                            
                            {
                                "name":"Brand",
                                "value":"SAVAGE"
                            }
                            
                        ]
                    }
                    , 
                    {
                        "name":"SAVAGE 220 TURKEY 20GA | 011356573834",
                        "image": "https://cdn-cumulusdata.celerantwebservices.com/SSPRODIMAGES/109786.jpg",
                        "available":"Out of Stock",
                        "id":"59536",
                        "brand":"SAVAGE",
                        "upc":"011356573834",
                        
                        "price":null,
                        "Dept":"Firearms",
                        "Typ":"Shotguns",
                        "SUBTYP_1":"Bolt",
                        "product_url":"/product/59536/SAVAGE220TURKEY20GA",
                        
                        "attributes": 
                        [
                            
                                {
                                    "name":"Pickup In Store",
                                    "value":"Not Available"
                                },
                            
                                {
                                    "name":"Price Range",
                                    "value":"$501-$700"
                                },
                            
                            {
                                "name":"Brand",
                                "value":"SAVAGE"
                            }
                            
                        ]
                    }
                    , 
                    {
                        "name":"MOSSBERG SA410 TRKY MOB 26 4RD | 884110757951",
                        "image": "https://cdn-cumulusdata.celerantwebservices.com/SSPRODIMAGES/123024.jpg",
                        "available":"Out of Stock",
                        "id":"264534",
                        "brand":"MOSSBERG",
                        "upc":"884110757951",
                        
                        "price":null,
                        "Dept":"Firearms",
                        "Typ":"Shotguns",
                        "SUBTYP_1":"Bolt",
                        "product_url":"/product/264534/MOSSBERGSA410TRKYMOB264RD",
                        
                        "attributes": 
                        [
                            
                                {
                                    "name":"Pickup In Store",
                                    "value":"Not Available"
                                },
                            
                                {
                                    "name":"Price Range",
                                    "value":"$501-$700"
                                },
                            
                            {
                                "name":"Brand",
                                "value":"MOSSBERG"
                            }
                            
                        ]
                    }
                    , 
                    {
                        "name":"MOSSBERG SA410 FLD BLK 26 4RD | 884110757968",
                        "image": "https://cdn-cumulusdata.celerantwebservices.com/SSPRODIMAGES/120479.jpg",
                        "available":"Out of Stock",
                        "id":"264587",
                        "brand":"MOSSBERG",
                        "upc":"884110757968",
                        
                        "price":null,
                        "Dept":"Firearms",
                        "Typ":"Shotguns",
                        "SUBTYP_1":"Bolt",
                        "product_url":"/product/264587/MOSSBERGSA410FLDBLK264RD",
                        
                        "attributes": 
                        [
                            
                                {
                                    "name":"Pickup In Store",
                                    "value":"Not Available"
                                },
                            
                                {
                                    "name":"Price Range",
                                    "value":"$501-$700"
                                },
                            
                            {
                                "name":"Brand",
                                "value":"MOSSBERG"
                            }
                            
                        ]
                    }
                    
        ]
    
